AutoFeedback/__init__.py
AutoFeedback/_version.py
AutoFeedback/answerchecks.py
AutoFeedback/bcolors.py
AutoFeedback/funcchecks.py
AutoFeedback/function_error_messages.py
AutoFeedback/plot_error_messages.py
AutoFeedback/plotchecks.py
AutoFeedback/plotclass.py
AutoFeedback/randomclass.py
AutoFeedback/utils.py
AutoFeedback/varchecks.py
AutoFeedback/variable_error_messages.py
autofeedback-2.22.dist-info/licenses/AUTHORS.rst
autofeedback-2.22.dist-info/licenses/LICENSE
test/__init__.py
test/printtest.py
test/testerrors.py
test/testfuncs.py
test/testplot.py
test/testplotclass.py
test/testprint.py
test/testrandomclass.py
test/testsymp.py
test/testutils.py
test/testvars.py
autofeedback-2.22.dist-info/METADATA
autofeedback-2.22.dist-info/WHEEL
autofeedback-2.22.dist-info/top_level.txt
autofeedback-2.22.dist-info/RECORD
