Metadata-Version: 2.4
Name: autofeedback
Version: 2.22
Summary: check basic python exercises with pretty feedback
Author-email: Andrew Brown <andrew.brown@qub.ac.uk>
License: BSD-3-Clause
Project-URL: Homepage, https://github.com/abrown41/AutoFeedback
Project-URL: Repository, https://github.com/abrown41/AutoFeedback
Classifier: Development Status :: 2 - Pre-Alpha
Classifier: Natural Language :: English
Classifier: Programming Language :: Python :: 3
Classifier: License :: OSI Approved :: BSD License
Requires-Python: >=3.7
License-File: LICENSE
License-File: AUTHORS.rst
Requires-Dist: numpy
Requires-Dist: scipy
Requires-Dist: multipledispatch
Requires-Dist: sympy
Requires-Dist: matplotlib
Provides-Extra: dev
Requires-Dist: codecov; extra == "dev"
Requires-Dist: coverage[toml]; extra == "dev"
Requires-Dist: ruff; extra == "dev"
Requires-Dist: twine; extra == "dev"
Requires-Dist: setuptools; extra == "dev"
Requires-Dist: wheel; extra == "dev"
Requires-Dist: ipython; extra == "dev"
Provides-Extra: docs
Requires-Dist: sphinx>=7.0; extra == "docs"
Requires-Dist: numpydoc; extra == "docs"
Requires-Dist: docutils>=0.17; extra == "docs"
Requires-Dist: sphinx-copybutton; extra == "docs"
Requires-Dist: sphinx-rtd-theme; extra == "docs"
Requires-Dist: sphinx-autoapi>=3.0; extra == "docs"
Dynamic: license-file
